{
  "card_effect": "【出】《蓝》: 将我方分身牌组1张使用时机包含[主要阶段]且费用合计为3以下的蓝色必杀牌不支付费用使用。",
  "card_lines": "啊，早安。～皮璐璐可～",
  "card_lrig_type": "皮璐璐可",
  "card_name": "代号 皮璐璐可·E",
  "card_no": "WXN01-SC045",
  "card_sprite_type": "",
  "card_type": "分身",
  "coin": "",
  "color": "蓝",
  "cost": "",
  "env": "SC",
  "faq": "",
  "goods_name": "WIXOSS简体中文版超世代强化包01",
  "grow_price": "蓝1",
  "level": "2",
  "limit": "4",
  "power": "",
  "rarity": "LC",
  "story": "",
  "team": "",
  "uid": "01H7VN3TCFSD82583EXA2YG2E8"
}
