{
  "card_effect": "【常】: 跳过我方成长阶段。\n【常】: 我方回合中，我方场上所有精灵的力量+5000。\n【起】《红》《红》《红》: 此回合，对方不能用等级2以下的精灵牌进行【防御】。",
  "card_lines": "那份愿望，化作飞舞的灰烬吧。\n～花代～",
  "card_lrig_type": "花代",
  "card_name": "轰炎 花代·贰改",
  "card_no": "WXN01-SC007",
  "card_sprite_type": "",
  "card_type": "分身",
  "coin": "",
  "color": "红",
  "cost": "",
  "env": "SC",
  "faq": "",
  "goods_name": "WIXOSS简体中文版超世代强化包01",
  "grow_price": "红2",
  "level": "2",
  "limit": "6",
  "power": "",
  "rarity": "LR",
  "story": "",
  "team": "",
  "uid": "01H7VN3WPKVFCBKS0286VWDVHQ"
}
