{
  "card_effect": "【常】: 只要该精灵的力量为10000以上，获得【枪兵】能力。\n【自】: 该牌因我方效果从手牌展示时，以我方场上1只＜水兽＞精灵为对象，可以支付《绿》并丢弃手牌1张《幻水 蛇颈龙》。若如此做，直到回合结束为止，其获得【枪兵】能力。\n生命爆发: 选择其中1项。①以对方场上1只力量为12000以上的精灵为对象，将其破坏。②【能量填充１】",
  "card_lines": "那片大海连接着少年的未来。",
  "card_lrig_type": "",
  "card_name": "幻水 蛇颈龙",
  "card_no": "WXN03-SC111",
  "card_sprite_type": "精生/水兽",
  "card_type": "精灵",
  "coin": "",
  "color": "绿",
  "cost": "",
  "env": "SC",
  "faq": "",
  "goods_name": "《WIXOSS》简体中文版超世代强化包03",
  "grow_price": "",
  "level": "3",
  "limit": "",
  "power": "7000",
  "rarity": "R",
  "story": "",
  "team": "",
  "uid": "01H7VM89N5QF94S6YQAK3991EA"
}
