{
  "card_effect": "【常】：只要对方场上有力量为7000以上的精灵，该精灵的基本力量变为8000。",
  "card_lines": "淅沥，淅沥，水中的工作也要进行。~§W 蚂蚁§~",
  "card_lrig_type": "",
  "card_name": "幻虫 §W蚂蚁§",
  "card_no": "WXD07-SC027-A",
  "card_sprite_type": "精生/凶虫",
  "card_type": "精灵",
  "coin": "",
  "color": "蓝",
  "cost": "",
  "env": "SC",
  "faq": "",
  "goods_name": "WIXOSSTCG简体中文版起始牌组07千嗤万蠷",
  "grow_price": "",
  "level": "2",
  "limit": "",
  "power": "5000",
  "rarity": "ST",
  "story": "",
  "team": "",
  "uid": "01H7X21AM3B9X7Q7RZ73YQ2R66"
}
