{
  "card_effect": "【连锁】《绿》《蓝》\n从以下4项选择最多2项。\n①以对方场上最多2只精灵为对象，将其横置。\n②以我方能量区最多2张牌为对象，将其加入手牌。\n③将我方牌组顶2张牌放置到能量区。\n④抽2张牌。",
  "card_lines": "选择的前方，想为你实现心之所愿。",
  "card_lrig_type": "",
  "card_name": "水天一碧",
  "card_no": "WXN03-SC013",
  "card_sprite_type": "",
  "card_type": "必杀",
  "coin": "",
  "color": "绿",
  "cost": "绿1蓝1无2",
  "env": "SC",
  "faq": "",
  "goods_name": "《WIXOSS》简体中文版超世代强化包03",
  "grow_price": "",
  "level": "",
  "limit": "",
  "power": "",
  "rarity": "LR",
  "story": "",
  "team": "",
  "uid": "01H7VM89AKX7RNXTF3SYRTM2XW"
}
