{
  "card_effect": "【出】：丢弃手牌1张<宇宙>精灵牌：从我方牌组检索1张等级与用此方法丢弃的精灵牌相同的精灵牌，将其展示并加入手牌，洗切牌组。\n生命爆发：抽1张牌。",
  "card_lines": "反射闪光！~≡反射率≡~\n哇，好闪。~北落师门~",
  "card_lrig_type": "",
  "card_name": "罗星 ≡反射率≡",
  "card_no": "WXD06-SCP008",
  "card_sprite_type": "精罗/宇宙",
  "card_type": "精灵",
  "coin": "",
  "color": "红",
  "cost": "",
  "env": "SC",
  "faq": "",
  "goods_name": "WIXOSSTCG简体中文版起始牌组06星宇宙之轮演",
  "grow_price": "",
  "level": "3",
  "limit": "",
  "power": "7000",
  "rarity": "SP",
  "story": "",
  "team": "",
  "uid": "01H7X21NS2G87M96J6RDQZ1J4K"
}
