{
  "card_effect": "以我方场上1只精灵为对象，将其破坏。若如此做，从我方牌组检索1张《MAGIC HAND》以外的魔法牌展示并加入手牌，洗切牌组。",
  "card_lines": "拿来吧你!~米璐璐恩~",
  "card_lrig_type": "",
  "card_name": "ＭＡＧＩＣ　ＨＡＮＤ",
  "card_no": "PR-SC028",
  "card_sprite_type": "",
  "card_type": "魔法",
  "coin": "",
  "color": "蓝",
  "cost": "蓝0",
  "env": "SC",
  "faq": "",
  "goods_name": "《WIXOSS》线下店铺比赛物料卡（银包）",
  "grow_price": "",
  "level": "",
  "limit": "",
  "power": "",
  "rarity": "PR",
  "story": "",
  "team": "",
  "uid": "01H818JT9036TFB5804W7VN5R7"
}
