{
  "card_effect": "【自】：该精灵被破坏时，可以展示我方手牌2张魔法牌。若如此做，抽1张牌。\n【自】：我方的主要阶段开始时，展示我方牌组顶1张牌。若其为魔法牌，抽1张牌。",
  "card_lines": "「比平时更加的闪-耀。」",
  "card_lrig_type": "",
  "card_name": "技术代号 环形灯",
  "card_no": "WXDi-DSC03-017",
  "card_sprite_type": "奏械/电机",
  "card_type": "精灵",
  "coin": "",
  "color": "白",
  "cost": "",
  "env": "SC",
  "faq": "",
  "goods_name": "WIXOSS 简体中文版DIVA出道牌组03-Card Jockey",
  "grow_price": "",
  "level": "1",
  "limit": "",
  "power": "1000",
  "rarity": "ST",
  "story": "",
  "team": "",
  "uid": "01HFCXQQSSMF8M67XXWJ6HBRVY"
}
