{
  "card_effect": "再演—丢弃手牌1张<美巧>精灵牌（可以追加支付再演费用使用。若如此做，该牌追加获得「将该牌返回分身牌组。」）\n\n以对方的1只精灵为对象，将其返回手牌。",
  "card_lines": "",
  "card_lrig_type": "",
  "card_name": "彫心镂骨",
  "card_no": "SPEX2-SC029",
  "card_sprite_type": "",
  "card_type": "必杀",
  "coin": "",
  "color": "绿",
  "cost": "绿1白1无1",
  "env": "SC",
  "faq": "",
  "goods_name": "《WIXOSS》简体中文版选择者收藏包SPEX2",
  "grow_price": "",
  "level": "",
  "limit": "",
  "power": "",
  "rarity": "LC",
  "story": "无",
  "team": "无",
  "uid": "01HNFDSDEF2165VEES3DFM7D96"
}
