{
  "card_effect": "从以下3项选择1项。若我方主分身为<忆>，改为选择最多2项。\n①以对方的1只精灵为对象，将其横置，将对方的所有精灵冻结。\n②将我方牌组底1张牌放置到废弃区。若其为精灵牌，将其从废弃区出场。\n③将我方牌组底1张牌放置到废弃区。若其为精灵牌，将对方的所有与其等级相同的精灵横置。",
  "card_lines": "",
  "card_lrig_type": "",
  "card_name": "强运・设想",
  "card_no": "WXN06-SC028",
  "card_sprite_type": "",
  "card_type": "必杀",
  "coin": "",
  "color": "蓝",
  "cost": "蓝3",
  "env": "",
  "faq": "",
  "goods_name": "《WIXOSS》简体中文版 超世代强化包06",
  "grow_price": "",
  "level": "",
  "limit": "",
  "power": "",
  "rarity": "LC",
  "story": "无",
  "team": "",
  "uid": "01HYMTKNSHYW77GR0PN3434JT7"
}
