{
  "card_effect": "【常】：只要我方废弃区有魔法牌，该精灵的力量+4000。\n生命爆发：以我方废弃区1张不持有《防御》的等级2以下的精灵牌为对象，将其加入手牌或出场。",
  "card_lines": "",
  "card_lrig_type": "",
  "card_name": "技术代号 除湿器",
  "card_no": "WXDi-PSC02-131",
  "card_sprite_type": "奏械/电机",
  "card_type": "精灵",
  "coin": "",
  "color": "黑",
  "cost": "",
  "env": "SC/DIVA",
  "faq": "",
  "goods_name": "《WIXOSS》简体中文版 DIVA强化包02",
  "grow_price": "",
  "level": "1",
  "limit": "",
  "power": "3000",
  "rarity": "C",
  "story": "无",
  "team": "",
  "uid": "01J4RJPMDT7RAV693A0EWWWNSW"
}
