{
  "card_effect": "【自】：我方攻击阶段开始时，只要对方不支付《无》，直到回合结束为止，对方的所有精灵失去能力。\n生命爆发：直到回合结束为止，对方的所有精灵失去能力。抽1张牌。",
  "card_lines": "",
  "card_lrig_type": "",
  "card_name": "中罠　由佳佳//回忆",
  "card_no": "WXDi-PSC03-SC076",
  "card_sprite_type": "",
  "card_type": "精灵",
  "coin": "",
  "color": "",
  "cost": "",
  "env": "SC/DIVA",
  "faq": "",
  "goods_name": "《WIXOSS》简体中文版 DIVA强化包03",
  "grow_price": "",
  "level": "",
  "limit": "",
  "power": "",
  "rarity": "R",
  "story": "无",
  "team": "",
  "uid": "01J8YCRPQJCEH0VNA9MHT9CNG1"
}
