{
  "card_effect": "【常】：对方的攻击阶段中，只要我方手牌为4张以上，该精灵获得【暗影】能力。（该精灵不会被对方取为对象）\n【出】《硬币》《硬币》：抽1张牌。\n生命爆发：直到回合结束为止，对方的所有精灵失去能力。抽1张牌。",
  "card_lines": "",
  "card_lrig_type": "",
  "card_name": "幻白水　鳗鱼",
  "card_no": "WXDi-PSC03-SC096",
  "card_sprite_type": "",
  "card_type": "精灵",
  "coin": "",
  "color": "",
  "cost": "",
  "env": "SC/DIVA",
  "faq": "",
  "goods_name": "《WIXOSS》简体中文版 DIVA强化包03",
  "grow_price": "",
  "level": "",
  "limit": "",
  "power": "",
  "rarity": "C",
  "story": "无",
  "team": "",
  "uid": "01J8YCRPRX840XFSPXPN479DDX"
}
